{"cameraMode":{"drawMode":0,"name":"Shaded","section":"Shading Mode"},"sceneLighting":false,"audioPlay":false,"sceneViewState":{"m_AlwaysRefresh":false,"showFog":true,"showSkybox":false,"showFlares":true,"showImageEffects":true,"showParticleSystems":true,"showVisualEffectGraphs":true,"m_FxEnabled":true},"in2DMode":false,"pivot":{"x":480.0,"y":322.5,"z":0.0},"rotation":{"x":-0.14698576927185059,"y":-0.766480028629303,"z":0.18904204666614533,"w":-0.5959677696228027},"size":578.2786865234375,"orthographic":false}